cpsar/__init__.py
cpsar/ajson.py
cpsar/app.py
cpsar/auth.py
cpsar/clientlib.py
cpsar/cobol.py
cpsar/config.py
cpsar/controls.py
cpsar/db.py
cpsar/destroyable.py
cpsar/edi.py
cpsar/formulary.py
cpsar/fwimport.py
cpsar/hcfa.py
cpsar/hcfa1500.py
cpsar/invoice.py
cpsar/invoice_id.py
cpsar/invoice_pdf.py
cpsar/keys.py
cpsar/liberty.py
cpsar/mail.py
cpsar/migrate.py
cpsar/ncpdp.py
cpsar/ncpdp11.py
cpsar/pdf.py
cpsar/pg.py
cpsar/pl_invoice.py
cpsar/pricing.py
cpsar/pricing2.py
cpsar/print_invoice.py
cpsar/rebate.py
cpsar/report.py
cpsar/runtime.py
cpsar/sagel.py
cpsar/sales.py
cpsar/scsaflib.py
cpsar/session.py
cpsar/shell.py
cpsar/smartadvisor.py
cpsar/sql.py
cpsar/srlib.py
cpsar/srtx.py
cpsar/teamsupport.py
cpsar/test_pricing.py
cpsar/test_pricing2.py
cpsar/txlib.py
cpsar/txtype.py
cpsar/version.py
cpsar/workqueue.py
cpsar/ws.py
cpsar/wsgirun.py
cpsar/apps/__init__.py
cpsar/apps/ac_adjuster_search.py
cpsar/apps/ac_flip_rebill.py
cpsar/apps/ac_hide_workitem.py
cpsar/apps/ac_mark_sr_flag.py
cpsar/apps/add_adjudication.py
cpsar/apps/add_client.py
cpsar/apps/add_client_bill_rule.py
cpsar/apps/add_default_account_name.py
cpsar/apps/add_dispense_fee_rule.py
cpsar/apps/add_distribution_rule.py
cpsar/apps/add_payment.py
cpsar/apps/add_payment_type.py
cpsar/apps/add_report_code.py
cpsar/apps/add_trans_debit.py
cpsar/apps/add_trans_distribution.py
cpsar/apps/add_trans_note.py
cpsar/apps/add_writeoff.py
cpsar/apps/change_trans_invoice_id.py
cpsar/apps/change_tx_type.py
cpsar/apps/create_rebill_trans.py
cpsar/apps/credit_reversal_to_group.py
cpsar/apps/delete_payment_type.py
cpsar/apps/edi_scsaf_rebill.py
cpsar/apps/edi_scsaf_send.py
cpsar/apps/flip_freeze_sr.py
cpsar/apps/flip_rebill.py
cpsar/apps/import_liberty.py
cpsar/apps/import_pk.py
cpsar/apps/index.py
cpsar/apps/login.py
cpsar/apps/logout.py
cpsar/apps/mark_for_state_reporting.py
cpsar/apps/mark_reversal_credit.py
cpsar/apps/markup_distributions.py
cpsar/apps/override_pharmacist.py
cpsar/apps/patient.py
cpsar-2024.1065.dist-info/METADATA
cpsar-2024.1065.dist-info/WHEEL
cpsar-2024.1065.dist-info/top_level.txt
cpsar-2024.1065.dist-info/RECORD
